poetry_env_plugin/__init__.py
poetry_env_plugin-0.1.0.dist-info/entry_points.txt
poetry_env_plugin-0.1.0.dist-info/WHEEL
poetry_env_plugin-0.1.0.dist-info/METADATA
poetry_env_plugin-0.1.0.dist-info/RECORD
