Metadata-Version: 2.1
Name: poetry-env-plugin
Version: 0.1.0
Summary: A Poetry plugin to load environment variables from .env file
Author: Brian Jinwright
Author-email: bjinwright@qwigo.com
Requires-Python: >=3.10,<4.0
Classifier: Programming Language :: Python :: 3
Classifier: Programming Language :: Python :: 3.10
Classifier: Programming Language :: Python :: 3.11
Requires-Dist: poetry (>=1.5.1,<2.0.0)
